.gitignore
.hgignore
MANIFEST.in
bootstrap.py
buildout.cfg
setup.py
doc/HACKING.txt
doc/NEWS.txt
doc/README.txt
src/bp/__init__.py
src/bp.convert.movie.egg-info/PKG-INFO
src/bp.convert.movie.egg-info/SOURCES.txt
src/bp.convert.movie.egg-info/dependency_links.txt
src/bp.convert.movie.egg-info/entry_points.txt
src/bp.convert.movie.egg-info/namespace_packages.txt
src/bp.convert.movie.egg-info/not-zip-safe
src/bp.convert.movie.egg-info/requires.txt
src/bp.convert.movie.egg-info/top_level.txt
src/bp/convert/__init__.py
src/bp/convert/movie/__init__.py
src/bp/convert/movie/handbrake.py