Metadata-Version: 1.0
Name: bp.convert.movie
Version: 0.1
Summary: Command line utility to ease movie conversion with HandBrakeCLI
Home-page: http://github.com/disko/bp.convert.movie
Author: Andreas Kaiser
Author-email: disko@binary-punks.com
License: BSD
Platform: UNKNOWN
Classifier: Programming Language :: Python
Classifier: Development Status :: 2 - Pre-Alpha
Classifier: Environment :: Console
Classifier: Intended Audience :: End Users/Desktop
Classifier: License :: OSI Approved :: BSD License
Classifier: Operating System :: POSIX
Classifier: Topic :: Utilities
